autoagents_deep_research/__init__.py
autoagents_deep_research-0.1.1.dist-info/METADATA
autoagents_deep_research-0.1.1.dist-info/WHEEL
autoagents_deep_research-0.1.1.dist-info/entry_points.txt
autoagents_deep_research-0.1.1.dist-info/RECORD
